qrmfinal_xd/VaR.py
qrmfinal_xd/__init__.py
qrmfinal_xd/cal.py
qrmfinal_xd/matrix.py
qrmfinal_xd/option_cal.py
qrmfinal_xd/portfolio_cal.py
qrmfinal_xd/regression.py
qrmfinal_xd/risk_cal.py
qrmfinal_xd/sim_copula.py
qrmfinal_xd-0.2.1.dist-info/METADATA
qrmfinal_xd-0.2.1.dist-info/WHEEL
qrmfinal_xd-0.2.1.dist-info/RECORD
